{
  "name": "Aziza Muhammad",
  "phone": "313-677-9942",
  "email": "aziza.muhammadx@gmail.com",
  "linkedin": "linkedin.com/in/aziza-m",
  "headline": "3yr B2B SDR | FinTech/AI-ML/LegalTech | IT degree + AWS + Security cert",
  "current_role": "SDR at Glen Coco (Oct 2024-Present)",
  "current_stats": "75+ daily outbound cold calls to C-level on Orum, 1-3 meetings booked per day, $10-15K deal sizes",
  "verticals_active": [
    "FinTech",
    "AI/ML",
    "Internet",
    "AdTech",
    "Payment Software",
    "LegalTech",
    "construction"
  ],
  "tools": [
    "HubSpot",
    "Salesforce",
    "Microsoft Dynamics 365",
    "Salesloft",
    "Apollo",
    "Apollo.io",
    "ZoomInfo",
    "Hunter.io",
    "ActiveCampaign",
    "Mailshake",
    "Outreach",
    "Orum",
    "InsideView",
    "Lead411",
    "Aircall",
    "Dialpad",
    "Microsoft Teams",
    "WebEx",
    "Power BI",
    "InsightSquared",
    "Nooks",
    "Sprout Social"
  ],
  "certifications": ["CompTIA A+", "CompTIA Security+", "AWS"],
  "education": "BS Information Technology, Eastern Gateway Community College, 2021",
  "skills": [
    "cold calling",
    "cold email",
    "lead qualification",
    "outbound prospecting",
    "CRM",
    "pipeline management",
    "discovery meetings",
    "appointment setting"
  ],
  "differentiators": [
    "BS in IT plus AWS and CompTIA Security certifications — rare technical credentials in the SDR pool, especially valuable for devtools, security, and AI/ML SaaS",
    "4+ years construction-sector outbound experience at 123 Go Staff — directly applicable to construction-SaaS",
    "Multi-vertical B2B SaaS exposure (FinTech, AI/ML, LegalTech, Payment Software, AdTech) at current Glen Coco SDR seat"
  ]
}
